flit/__init__.py
flit/__main__.py
flit/_get_dirs.py
flit/build.py
flit/buildapi.py
flit/inifile.py
flit/init.py
flit/install.py
flit/installfrom.py
flit/log.py
flit/logo.py
flit/sdist.py
flit/tomlify.py
flit/upload.py
flit/validate.py
flit/wheel.py
flit/license_templates/apache
flit/license_templates/gpl3
flit/license_templates/mit
flit/vcs/__init__.py
flit/vcs/git.py
flit/vcs/hg.py
flit/vendorized/__init__.py
flit/vendorized/readme/__init__.py
flit/vendorized/readme/clean.py
flit/vendorized/readme/rst.py
dflit-2.3.0.1.dist-info/entry_points.txt
dflit-2.3.0.1.dist-info/LICENSE
dflit-2.3.0.1.dist-info/WHEEL
dflit-2.3.0.1.dist-info/METADATA
dflit-2.3.0.1.dist-info/RECORD
