Metadata-Version: 2.1
Name: dflit
Version: 2.3.0.1
Summary: A simple packaging tool for simple packages.
Home-page: https://github.com/davidfritzsche/dflit
License: UNKNOWN
Author: David Fritzsche / flit by Thomas Kluyver
Author-email: david.fritzsche@mvua.de
Requires-Python: >=3.5
Classifier: Intended Audience :: Developers
Classifier: License :: OSI Approved :: BSD License
Classifier: Programming Language :: Python :: 3
Classifier: Topic :: Software Development :: Libraries :: Python Modules
Requires-Dist: dflit_core>=2.3.0.1
Requires-Dist: requests
Requires-Dist: docutils
Requires-Dist: pytoml
Requires-Dist: zipfile36; python_version in '3.3 3.4 3.5'
Requires-Dist: sphinx ; extra == "doc"
Requires-Dist: sphinxcontrib_github_alt ; extra == "doc"
Requires-Dist: pygments-github-lexers ; extra == "doc"
Requires-Dist: requests_download ; extra == "installfrom"
Requires-Dist: testpath ; extra == "test"
Requires-Dist: responses ; extra == "test"
Requires-Dist: pytest>=2.7.3 ; extra == "test"
Requires-Dist: pytest-cov ; extra == "test"
Project-URL: Documentation, https://flit.readthedocs.io/en/latest/
Provides-Extra: doc
Provides-Extra: installfrom
Provides-Extra: test
